getlicense.py
getlicense-0.4.1.dist-info/LICENSE
getlicense-0.4.1.dist-info/METADATA
getlicense-0.4.1.dist-info/WHEEL
getlicense-0.4.1.dist-info/entry_points.txt
getlicense-0.4.1.dist-info/RECORD
