Metadata-Version: 2.3
Name: getlicense
Version: 0.4.1
Summary: A tool to quickly generate software license files with customizable project details
Author: Ashkan Feyzollahi
Author-email: ashkanfeyzollahi@gmail.com
Requires-Python: >=3.13
Classifier: Programming Language :: Python :: 3
Classifier: Programming Language :: Python :: 3.13
Requires-Dist: appdirs (>=1.4.4,<2.0.0)
Requires-Dist: requests (>=2.32.4,<3.0.0)
Project-URL: Repository, https://github.com/ashkanfeyzollahi/getlicense
